unpact/__init__.py
unpact/classes/__init__.py
unpact/classes/tree.py
unpact/classes/unpacker.py
unpact/constants/__init__.py
unpact/py.typed
unpact/types/__init__.py
unpact/types/columns.py
unpact/types/formatters.py
unpact/types/values.py
unpact/unwind_util.py
unpact/utils/__init__.py
unpact/utils/column_defs.py
unpact/utils/tree.py
unpact-0.0.20.dist-info/LICENSE
unpact-0.0.20.dist-info/METADATA
unpact-0.0.20.dist-info/WHEEL
unpact-0.0.20.dist-info/RECORD
