Metadata-Version: 2.3
Name: unpact
Version: 0.0.20
Summary: A lightweight library for tabulating dictionaries
License: MIT
Keywords: tables,formatting,flat,flattening,json
Author: Moph Toyer
Author-email: chris@telemetry.fm
Requires-Python: >=3.9,<4.0
Classifier: License :: OSI Approved :: MIT License
Classifier: Programming Language :: Python :: 3
Classifier: Programming Language :: Python :: 3.9
Classifier: Programming Language :: Python :: 3.10
Classifier: Programming Language :: Python :: 3.11
Classifier: Programming Language :: Python :: 3.12
Classifier: Programming Language :: Python :: 3.13
Requires-Dist: typing-extensions (>=4.8.0,<5.0.0)
